Sqlalchemy13ZhongwenWendang/README.md
Sqlalchemy13ZhongwenWendang/__init__.py
Sqlalchemy13ZhongwenWendang/__main__.py
Sqlalchemy13ZhongwenWendang/file.epub
Sqlalchemy13ZhongwenWendang/index.html
Sqlalchemy13ZhongwenWendang/css/__init__.py
Sqlalchemy13ZhongwenWendang/css/annotations.css
Sqlalchemy13ZhongwenWendang/css/main.css
Sqlalchemy13ZhongwenWendang/css/normalize.css
Sqlalchemy13ZhongwenWendang/css/popup.css
Sqlalchemy13ZhongwenWendang/font/__init__.py
Sqlalchemy13ZhongwenWendang/font/fontello.eot
Sqlalchemy13ZhongwenWendang/font/fontello.svg
Sqlalchemy13ZhongwenWendang/font/fontello.ttf
Sqlalchemy13ZhongwenWendang/font/fontello.woff
Sqlalchemy13ZhongwenWendang/img/__init__.py
Sqlalchemy13ZhongwenWendang/img/annotator-glyph-sprite.png
Sqlalchemy13ZhongwenWendang/img/annotator-icon-sprite.png
Sqlalchemy13ZhongwenWendang/img/apple-touch-icon.png
Sqlalchemy13ZhongwenWendang/img/cancelfullscreen.png
Sqlalchemy13ZhongwenWendang/img/close.png
Sqlalchemy13ZhongwenWendang/img/fullscreen.png
Sqlalchemy13ZhongwenWendang/img/loader.gif
Sqlalchemy13ZhongwenWendang/img/menu-icon.png
Sqlalchemy13ZhongwenWendang/img/save.png
Sqlalchemy13ZhongwenWendang/img/saved.png
Sqlalchemy13ZhongwenWendang/img/settings-s.png
Sqlalchemy13ZhongwenWendang/img/settings.png
Sqlalchemy13ZhongwenWendang/img/star.png
Sqlalchemy13ZhongwenWendang/js/__init__.py
Sqlalchemy13ZhongwenWendang/js/epub.js
Sqlalchemy13ZhongwenWendang/js/epub.min.js
Sqlalchemy13ZhongwenWendang/js/epub.min.map
Sqlalchemy13ZhongwenWendang/js/hooks.min.js
Sqlalchemy13ZhongwenWendang/js/hooks.min.map
Sqlalchemy13ZhongwenWendang/js/reader.js
Sqlalchemy13ZhongwenWendang/js/reader.js.map
Sqlalchemy13ZhongwenWendang/js/reader.min.js
Sqlalchemy13ZhongwenWendang/js/reader.min.map
Sqlalchemy13ZhongwenWendang/js/hooks/__init__.py
Sqlalchemy13ZhongwenWendang/js/hooks/extensions/__init__.py
Sqlalchemy13ZhongwenWendang/js/hooks/extensions/highlight.js
Sqlalchemy13ZhongwenWendang/js/libs/__init__.py
sqlalchemy_1_3_zhongwen_wendang-2024.3.5.0.dist-info/METADATA
sqlalchemy_1_3_zhongwen_wendang-2024.3.5.0.dist-info/WHEEL
sqlalchemy_1_3_zhongwen_wendang-2024.3.5.0.dist-info/entry_points.txt
sqlalchemy_1_3_zhongwen_wendang-2024.3.5.0.dist-info/top_level.txt
sqlalchemy_1_3_zhongwen_wendang-2024.3.5.0.dist-info/RECORD
